contextgraph/__init__.py
contextgraph/csv_importer.py
contextgraph/cypher_parser.py
contextgraph/exceptions.py
contextgraph/graphdb.py
contextgraph/py.typed
contextgraph/query_result.py
contextgraph/transaction.py
contextgraph/visualization.py
contextgraph-0.3.1.dist-info/licenses/LICENSE
contextgraph-0.3.1.dist-info/METADATA
contextgraph-0.3.1.dist-info/WHEEL
contextgraph-0.3.1.dist-info/top_level.txt
contextgraph-0.3.1.dist-info/RECORD
