Metadata-Version: 2.4
Name: contextgraph
Version: 0.3.1
Summary: A powerful graph database with Cypher query support and advanced visualization capabilities
Home-page: https://github.com/shaileshj2803/contextgraph
Author: Shailesh Jannu
Author-email: shaileshj@gmail.com
License: MIT
Project-URL: Bug Reports, https://github.com/shaileshj2803/contextgraph/issues
Project-URL: Source, https://github.com/shaileshj2803/contextgraph
Project-URL: Documentation, https://github.com/shaileshj2803/contextgraph#readme
Keywords: graph database cypher context visualization networkx
Classifier: Development Status :: 4 - Beta
Classifier: Intended Audience :: Developers
Classifier: Intended Audience :: Science/Research
Classifier: License :: OSI Approved :: MIT License
Classifier: Operating System :: OS Independent
Classifier: Programming Language :: Python :: 3
Classifier: Programming Language :: Python :: 3.8
Classifier: Programming Language :: Python :: 3.9
Classifier: Programming Language :: Python :: 3.10
Classifier: Programming Language :: Python :: 3.11
Classifier: Programming Language :: Python :: 3.12
Classifier: Topic :: Database
Classifier: Topic :: Scientific/Engineering :: Information Analysis
Classifier: Topic :: Software Development :: Libraries :: Python Modules
Requires-Python: >=3.8
License-File: LICENSE
Requires-Dist: igraph>=0.10.0
Requires-Dist: pyparsing>=3.0.0
Provides-Extra: visualization
Requires-Dist: matplotlib>=3.5.0; extra == "visualization"
Requires-Dist: networkx>=2.6.0; extra == "visualization"
Requires-Dist: plotly>=5.0.0; extra == "visualization"
Provides-Extra: graphviz
Requires-Dist: graphviz>=0.19.0; extra == "graphviz"
Provides-Extra: dev
Requires-Dist: pytest>=6.0.0; extra == "dev"
Requires-Dist: pytest-cov>=2.10.0; extra == "dev"
Requires-Dist: flake8>=3.8.0; extra == "dev"
Requires-Dist: black>=21.0.0; extra == "dev"
Requires-Dist: mypy>=0.800; extra == "dev"
Provides-Extra: all
Requires-Dist: matplotlib>=3.5.0; extra == "all"
Requires-Dist: networkx>=2.6.0; extra == "all"
Requires-Dist: plotly>=5.0.0; extra == "all"
Requires-Dist: graphviz>=0.19.0; extra == "all"
Dynamic: author
Dynamic: author-email
Dynamic: classifier
Dynamic: description
Dynamic: description-content-type
Dynamic: home-page
Dynamic: keywords
Dynamic: license
Dynamic: license-file
Dynamic: project-url
Dynamic: provides-extra
Dynamic: requires-dist
Dynamic: requires-python
Dynamic: summary
